LICENSE
MANIFEST.in
README.rst
setup.cfg
setup.py
csvmaker/__init__.py
csvmaker/utils.py
django_csvmaker.egg-info/PKG-INFO
django_csvmaker.egg-info/SOURCES.txt
django_csvmaker.egg-info/dependency_links.txt
django_csvmaker.egg-info/requires.txt
django_csvmaker.egg-info/top_level.txt